LICENSE
MANIFEST.in
README.md
pyproject.toml
setup.py
p3dpy/__init__.py
p3dpy/assignment.py
p3dpy/feature.py
p3dpy/filter.py
p3dpy/io.py
p3dpy/pointcloud.py
p3dpy/registration.py
p3dpy/rgbdimage.py
p3dpy/run_vizserver.py
p3dpy/segmentation.py
p3dpy/vizclient.py
p3dpy.egg-info/PKG-INFO
p3dpy.egg-info/SOURCES.txt
p3dpy.egg-info/dependency_links.txt
p3dpy.egg-info/entry_points.txt
p3dpy.egg-info/not-zip-safe
p3dpy.egg-info/requires.txt
p3dpy.egg-info/top_level.txt
p3dpy/app/__init__.py
p3dpy/app/cli.py
p3dpy/app/vizserver.py
p3dpy/app/static/css/style.css
p3dpy/app/static/js/OrbitControls.js
p3dpy/app/static/js/dat.gui.module.js
p3dpy/app/static/js/stats.module.js
p3dpy/app/static/js/three.js
p3dpy/app/templates/index.html