Metadata-Version: 2.1
Name: p3dpy
Version: 0.13.0
Summary: Simple pointcloud toolkit and browser based viewer
Home-page: http://github.com/neka-nat/p3dpy
Author: neka-nat
Author-email: nekanat.stock@gmail.com
License: MIT
Keywords: pointcloud
Platform: UNKNOWN
License-File: LICENSE
